malariagen/__init__.py
malariagen/cloud/__init__.py
malariagen/data/__init__.py
malariagen/tests/test_cloud.py
malariagen/tests/test_data.py
malariagen/tests/test_package.py
malariagen-0.0.1.dist-info/LICENSE.txt
malariagen-0.0.1.dist-info/METADATA
malariagen-0.0.1.dist-info/WHEEL
malariagen-0.0.1.dist-info/RECORD
